setup.py
riak_statsd/__init__.py
riak_statsd/transport.py
riak_statsd.egg-info/PKG-INFO
riak_statsd.egg-info/SOURCES.txt
riak_statsd.egg-info/dependency_links.txt
riak_statsd.egg-info/requires.txt
riak_statsd.egg-info/top_level.txt