Metadata-Version: 1.0
Name: riak-statsd
Version: 0.1.0
Summary: Transport proxy for instrumenting Riak clients
Home-page: https://github.com/aluzzardi/riak-statsd-python
Author: Andrea Luzzardi
Author-email: andrea@luzzardi.com
License: UNKNOWN
Platform: UNKNOWN
Classifier: Programming Language :: Python
Classifier: Development Status :: 4 - Beta
Classifier: Environment :: Other Environment
Classifier: Intended Audience :: Developers
Classifier: License :: OSI Approved :: MIT License
Classifier: Operating System :: OS Independent
Classifier: Topic :: Software Development :: Libraries :: Python Modules
